Metadata-Version: 1.0
Name: sherlockml
Version: 0.18.6
Summary: Python library for interacting with SherlockML.
Home-page: https://sherlockml.com
Author: ASI Data Science
Author-email: opensource@asidatascience.com
License: Apache Software License
Platform: UNKNOWN
